[
  {
    "id": "AeHIrLTr6JkxGE6SN-0Rw",
    "name": "Allen Raymond",
    "email": "nulla.ante@vestibul.co.uk",
    "phone": "(992) 914-3792"
  },
  {
    "id": "qdggE76Jtbfd9eWJHrssH",
    "name": "Alec ",
    "email": "Done",
    "phone": "8884444666"
  },
  {
    "id": "drsAJ4SHPYqZeG-83QTVW",
    "name": "Kennedy Lane",
    "email": "mattis.Cras@nonenimMauris.net",
    "phone": "(542) 451-7038"
  },
  {
    "id": "vza2RIzNGIwutCVCs4mCL",
    "name": "Wylie Pope",
    "email": "est@utquamvel.net",
    "phone": "(692) 802-2949"
  },
  {
    "id": "05olLMgyVQdWRwgKfg5J6",
    "name": "Cyrus Jackson",
    "email": "nibh@semsempererat.com",
    "phone": "(501) 472-5218"
  },
  {
    "id": "1DEXoP8AuCGYc1YgoQ6hw",
    "name": "Abbot Franks",
    "email": "scelerisque@magnis.org",
    "phone": "(186) 568-3720"
  },
  {
    "id": "Z5sbDlS7pCzNsnAHLtDJd",
    "name": "Reuben Henry",
    "email": "pharetra.ut@dictum.co.uk",
    "phone": "(715) 598-5792"
  },
  {
    "id": "C9sjBfCo4UJCWjzBnOtxl",
    "name": "Simon Morton",
    "email": "dui.Fusce.diam@Donec.com",
    "phone": "(233) 738-2360"
  },
  {
    "id": "e6ywwRe4jcqxXfCZOj_1e",
    "name": "Thomas Lucas",
    "email": "nec@Nulla.com",
    "phone": "(704) 398-7993"
  },
  {
    "id": "rsKkOQUi80UsgVPCcLZZW",
    "name": "Alec Howard",
    "email": "Donec.elementum@scelerisquescelerisquedui.net",
    "phone": "(748) 206-2688"
  },
  {
    "id": "6WF2qcPqhgVJi-YHmQLP5",
    "name": "aaa",
    "email": "Done",
    "phone": "888666"
  },
  {
    "id": "qX3YJl9G5X30847ZxT3nX",
    "name": "aaa",
    "email": "Done",
    "phone": "888666"
  },
  {
    "id": "gg59ko9F81Qvs94-PkcjG",
    "name": "aaa",
    "email": "Done",
    "phone": "888666"
  },
  {
    "id": "LMn3rZcoiVegGuCXHz26H",
    "name": "aaa",
    "email": "Done",
    "phone": "888666"
  },
  {
    "id": "P1GY1tLX3awVU8EaHbvAp",
    "name": "aaa",
    "email": "Done",
    "phone": "888666"
  },
  {
    "id": "AdLdJnLmF4s5y_UU6lTeg",
    "name": "aaa",
    "email": "Done",
    "phone": "888666"
  },
  {
    "id": "estZ1FAvCk9SPDdFZLa6u",
    "name": "aaa",
    "email": "Done",
    "phone": "888666"
  },
  {
    "id": "-bTGoK3otPnG9IKskDsI1",
    "name": "aaa",
    "email": "Done",
    "phone": "888666"
  },
  {
    "id": "eHh5xKCXrpCh_PV4CXVFW",
    "name": "aaa",
    "email": "Done",
    "phone": "888666"
  },
  {
    "id": "han0TQAazEma8v-ikrS9w",
    "name": "aaa",
    "email": "Done",
    "phone": "888666"
  },
  {
    "id": "Lt8xUQY9O_vs4w5Q_yYbq",
    "name": "aaa",
    "email": "Done",
    "phone": "888666"
  },
  {
    "id": "23OIoVE_kLrkQjsThvhQR",
    "name": "aaa",
    "email": "Done",
    "phone": "888666"
  },
  {
    "id": "JDSB7C1GUC0WCaG0Y8eFc",
    "name": "333 ",
    "email": "Done",
    "phone": "8884444666"
  },
  {
    "id": "fCV2NjSHyuieKsIdCSLSv",
    "name": "555",
    "email": "Done",
    "phone": "888666"
  },
  {
    "id": "GpTkKJnK3YWvGMuKvrNVc",
    "name": "555",
    "email": "Done",
    "phone": "888666"
  },
  {
    "id": "e7FnUNr7lZKFr0lKHQGtK",
    "name": "555",
    "email": "Done",
    "phone": "888666"
  },
  {
    "id": "VvY3zuwXn-vaHX1Cq7U1o",
    "name": "",
    "email": "Done",
    "phone": "888666"
  },
  {
    "id": "pSM4gBhf8t5iiE7XDDiSX",
    "name": "2222",
    "email": "Done",
    "phone": "888666"
  },
  {
    "id": "u9AMcRcMLLQG9nFx17nGb",
    "name": "{2222}",
    "email": "Done",
    "phone": "888666"
  },
  {
    "id": "_XKAuNsRWWNgv9_uI_iCd",
    "name": "222",
    "email": "Done",
    "phone": "888666"
  },
  {
    "id": "_Qe8Sr7trDAhh60SXZ3aR",
    "name": "",
    "email": "Done",
    "phone": "888666"
  },
  {
    "id": "da5dU8vqS9B8J5b-vXg43",
    "name": "555",
    "email": "Done",
    "phone": "888666"
  },
  {
    "id": "CZS_IAR120PFTKZnL1-0w",
    "name": "ccc",
    "email": "Done",
    "phone": "888666"
  },
  {
    "id": "pzK0vHByg2oDNKnrCI3_T",
    "name": "ccc",
    "email": "Done",
    "phone": "888666"
  },
  {
    "id": "lai4dMFdmRUCgpb0bwyF4",
    "name": "ccc",
    "email": "Done",
    "phone": "888666"
  },
  {
    "id": "zHzUnp-zClwLKlU2vadRx",
    "name": "",
    "email": "Done",
    "phone": "888666"
  },
  {
    "id": "Xhz0gMM2Sk2600TqKN0c-",
    "name": "",
    "email": "Done",
    "phone": "888666"
  },
  {
    "id": "0BbsGxCNMoT4-8-5JwGz0",
    "name": true,
    "email": "Done",
    "phone": "888666"
  },
  {
    "id": "MeVcTQnK1NOzqSgVBcIGr",
    "name": true,
    "email": "Done",
    "phone": "888666"
  },
  {
    "id": "YwqkhdWsFHDsQK7lrTuDp",
    "name": false,
    "email": "Done",
    "phone": "888666"
  },
  {
    "id": "oFao1x2SjqG2ms44Hcbpg",
    "name": "ddd",
    "email": "Done",
    "phone": "888666"
  },
  {
    "id": "cEkZP6ejLb3yCrNnuL3vD",
    "name": "ddd",
    "phone": "888666"
  },
  {
    "id": "L2PTENAbAwwTAPc3Hh3-I",
    "name": "ddd",
    "email": "Done",
    "phone": "888666"
  },
  {
    "id": "_iV0Uxp4PpE579Aq3Y2uK",
    "name": "ddd",
    "email": "Done",
    "phone": "888666"
  },
  {
    "id": "o_D_6zKMVUMs-D2fW3fHY",
    "name": "ddd",
    "email": "Done",
    "phone": "dd"
  },
  {
    "id": "d8iiWiXiHHEYntjtAFH6I",
    "name": "ddd",
    "email": "Done",
    "phone": "5555"
  },
  {
    "id": "BSaJI54LGPrBzUVpSYqt-",
    "name": "ddd",
    "email": "Done",
    "phone": "33"
  },
  {
    "id": "b5XakosIy1YUSMs4u9Qrx",
    "name": "ddd",
    "email": "Done",
    "phone": "33"
  },
  {
    "id": "OrNkGAS8bUd2pV5tuXCT2",
    "name": "ddd",
    "email": "Done",
    "phone": "33"
  },
  {
    "id": "gMNn-SfosvDGi9-JHKicO",
    "name": "ddd",
    "email": "Done",
    "phone": "55"
  },
  {
    "id": "NnsuftmgBuTK0oObIsAlJ",
    "name": "ddd",
    "email": "Done",
    "phone": "55"
  },
  {
    "id": "tOFMae_3Xvd2BVdNP_963",
    "name": "ddd",
    "email": "Done",
    "phone": "55"
  },
  {
    "id": "XvuHnvQ3fBdAo1E5wBxmA",
    "name": "ddd",
    "email": "Done",
    "phone": "858"
  }
]